{"cameraMode":{"drawMode":0,"name":"Shaded","section":"Shading Mode"},"sceneLighting":true,"audioPlay":false,"sceneViewState":{"m_AlwaysRefresh":false,"showFog":true,"showSkybox":true,"showFlares":true,"showImageEffects":true,"showParticleSystems":true,"showVisualEffectGraphs":true,"m_FxEnabled":true},"in2DMode":false,"pivot":{"x":5.342275142669678,"y":-0.6910907626152039,"z":-2.265320062637329},"rotation":{"x":-0.01094514038413763,"y":0.9833394885063171,"z":-0.17013141512870789,"w":-0.06385482847690582},"size":4.824949264526367,"orthographic":false}